[
    {
        "name":"Rakesh Jhunjhunwala",
        "img":"RakeshJhunjhunwala.png",
        "tagline":"He starting inversement in the 90's. His inversement st..."
    },
    {
        "name":"Anil Goel",
        "img":"AnilGoel.png",
        "tagline":"He starting inversement in the 90's. His inversement st..."
    },
    {
        "name":"Ashish Dhawan",
        "img":"AshishDhawan.png",
        "tagline":"He starting inversement in the 90's. His inversement st..."
    },
    {
        "name":"Ashish Kacholia",
        "img":"AshishKacholia.png",
        "tagline":"He starting inversement in the 90's. His inversement st..."
    },
    {
        "name":"Dolly Rajeev Khanna",
        "img":"DollyRajeevKhanna.png",
        "tagline":"He starting inversement in the 90's. His inversement st..."
    },
    {
        "name":"Hemendra Kothari",
        "img":"HemendraKothari.png",
        "tagline":"He starting inversement in the 90's. His inversement st..."
    },
    {
        "name":"Nemish Shah",
        "img":"NemishShah.png",
        "tagline":"He starting inversement in the 90's. His inversement st..."
    },
    {
        "name":"Porinju Veliyath",
        "img":"Porinju.png",
        "tagline":"He starting inversement in the 90's. His inversement st..."
    },
    {
        "name":"Radhakishan Damani",
        "img":"Radhakishan.png",
        "tagline":"He starting inversement in the 90's. His inversement st..."
    },
    {
        "name":"Sunil Singhania",
        "img":"Sunil.png",
        "tagline":"He starting inversement in the 90's. His inversement st..."
    },
    {
        "name":"Vijay Kedia",
        "img":"Vijay.png",
        "tagline":"He starting inversement in the 90's. His inversement st..."
    },
    {
        "name":"Anil Goel",
        "img":"Anil.png",
        "tagline":"He starting inversement in the 90's. His inversement st..."
    }
]